invest_calc/__init__.py
invest_calc/fin_calc.py
order_receipt/__init__.py
order_receipt/order_receipt.py
sales_report/__init__.py
sales_report/sales_report.py
transaction_report/__init__.py
transaction_report/transaction_report.py
order_receipt-0.1.0.dist-info/METADATA
order_receipt-0.1.0.dist-info/WHEEL
order_receipt-0.1.0.dist-info/top_level.txt
order_receipt-0.1.0.dist-info/RECORD
