Metadata-Version: 2.1
Name: order_receipt
Version: 0.1.0
Summary: Пакет для cоздания чеков
Author-email: mikhail <m.zimin@edu.centraluniversity.ru>
Requires-Dist: argparse
Requires-Dist: json
